mcmath/__init__.py
mcmath/eighth.py
mcmath/eleventh.py
mcmath/first.py
mcmath/fourth.py
mcmath/ninth.py
mcmath/second.py
mcmath/seventh.py
mcmath/sixth.py
mcmath/third.py
mcmath/thirteen.py
mcmath/twelve.py
mcmath-0.0.1.dist-info/METADATA
mcmath-0.0.1.dist-info/WHEEL
mcmath-0.0.1.dist-info/top_level.txt
mcmath-0.0.1.dist-info/RECORD
