Metadata-Version: 2.4
Name: mcmath
Version: 0.0.1
Summary: MCMATH
Home-page: https://github.com/alxprgs/mcmath
Author: Alx
Author-email: proshka20081010@gmail.com
Keywords: mcmath
Classifier: Programming Language :: Python :: 3.11
Classifier: License :: OSI Approved :: MIT License
Classifier: Operating System :: OS Independent
Requires-Python: >=3.10
Dynamic: author
Dynamic: author-email
Dynamic: classifier
Dynamic: description
Dynamic: description-content-type
Dynamic: home-page
Dynamic: keywords
Dynamic: requires-python
Dynamic: summary
